[
    {
        "tag": "greeting",
        "patterns": [
            "Hi",
            "Hello",
            "Hey",
            "How are you",
            "What's up"
        ],
        "responses": [
            "Hi there",
            "Hello",
            "Hey",
            "I'm fine, thank you",
            "Nothing much"
        ]
    },
    {
        "tag": "goodbye",
        "patterns": [
            "Bye",
            "See you later",
            "Goodbye",
            "Take care"
        ],
        "responses": [
            "Goodbye",
            "See you later",
            "Take care"
        ]
    },
    {
        "tag": "thanks",
        "patterns": [
            "Thank you",
            "Thanks",
            "Thanks a lot",
            "I appreciate it"
        ],
        "responses": [
            "You're welcome",
            "No problem",
            "Glad I could help"
        ]
    },
    {
        "tag": "about",
        "patterns": [
            "What can you do",
            "Who are you",
            "What are you",
            "What is your purpose"
        ],
        "responses": [
            "I am a chatbot",
            "My purpose is to assist you",
            "I can answer questions and provide assistance"
        ]
    },
    {
        "tag": "help",
        "patterns": [
            "Help",
            "I need help",
            "Can you help me",
            "What should I do"
        ],
        "responses": [
            "Sure, what do you need help with?",
            "I'm here to help. What's the problem?",
            "How can I assist you?"
        ]
    },
    {
        "tag": "age",
        "patterns": [
            "How old are you",
            "What's your age"
        ],
        "responses": [
            "I don't have an age. I'm a chatbot.",
            "I was just born in the digital world.",
            "Age is just a number for me."
        ]
    },
    {
        "tag": "weather",
        "patterns": [
            "What's the weather like",
            "How's the weather today"
        ],
        "responses": [
            "I'm sorry, I cannot provide real-time weather information.",
            "You can check the weather on a weather app or website."
        ]
    },
    {
        "tag": "budget",
        "patterns": [
            "How can I make a budget",
            "What's a good budgeting strategy",
            "How do I create a budget"
        ],
        "responses": [
            "To make a budget, start by tracking your income and expenses. Then, allocate your income towards essential expenses like rent, food, and bills. Next, allocate some of your income towards savings and debt repayment. Finally, allocate the remainder of your income towards discretionary expenses like entertainment and hobbies.",
            "A good budgeting strategy is to use the 50/30/20 rule. This means allocating 50% of your income towards essential expenses, 30% towards discretionary expenses, and 20% towards savings and debt repayment.",
            "To create a budget, start by setting financial goals for yourself. Then, track your income and expenses for a few months to get a sense of where your money is going. Next, create a budget by allocating your income towards essential expenses, savings and debt repayment, and discretionary expenses."
        ]
    },
    {
        "tag": "credit_score",
        "patterns": [
            "What is a credit score",
            "How do I check my credit score",
            "How can I improve my credit score"
        ],
        "responses": [
            "A credit score is a number that represents your creditworthiness. It is based on your credit history and is used by lenders to determine whether or not to lend you money. The higher your credit score, the more likely you are to be approved for credit.",
            "You can check your credit score for free on several websites such as Credit Karma and Credit Sesame."
        ]
    },
        {
            "tag": "artificial_intelligence",
            "patterns": [
                "Tell me about artificial intelligence",
                "What is AI",
                "How does AI work",
                "Applications of artificial intelligence"
            ],
            "responses": [
                "Artificial Intelligence (AI) refers to the simulation of human intelligence in machines that are programmed to think and learn.",
                "AI works through algorithms that process data, recognize patterns, and make decisions or predictions.",
                "AI is used in various fields such as healthcare, finance, transportation, and entertainment."
            ]
        },
        {
            "tag": "machine_learning",
            "patterns": [
                "What is machine learning",
                "How does machine learning work",
                "Applications of machine learning"
            ],
            "responses": [
                "Machine Learning is a subset of AI that enables systems to learn from data and improve performance without explicit programming.",
                "It works by using algorithms to analyze data, identify patterns, and make decisions or predictions.",
                "Machine Learning is applied in fields like recommendation systems, fraud detection, and image recognition."
            ]
        },
        {
            "tag": "blockchain",
            "patterns": [
                "Tell me about blockchain",
                "What is blockchain technology",
                "Applications of blockchain"
            ],
            "responses": [
                "Blockchain is a decentralized, distributed ledger technology used to securely record transactions across multiple computers.",
                "It is the backbone of cryptocurrencies like Bitcoin and Ethereum, but it is also used for supply chain management and secure data sharing.",
                "Blockchain offers transparency, security, and immutability in data management."
            ]
        },
        {
            "tag": "quantum_computing",
            "patterns": [
                "Tell me about quantum computing",
                "What is quantum computing",
                "How does quantum computing work"
            ],
            "responses": [
                "Quantum computing is a type of computing that uses quantum bits (qubits) to perform calculations much faster than traditional computers for certain tasks.",
                "It relies on principles of quantum mechanics, such as superposition and entanglement.",
                "Quantum computing has potential applications in cryptography, optimization problems, and complex simulations."
            ]
        },
        {
            "tag": "renewable_energy",
            "patterns": [
                "Tell me about renewable energy",
                "What are renewable energy sources",
                "Importance of renewable energy"
            ],
            "responses": [
                "Renewable energy comes from natural sources that are replenished constantly, such as solar, wind, hydro, and geothermal energy.",
                "It is important for reducing greenhouse gas emissions and combating climate change.",
                "Using renewable energy can help transition towards a more sustainable and eco-friendly future."
            ]
        },
        {
            "tag": "personal_finance",
            "patterns": [
                "Tell me about personal finance",
                "How to manage money effectively",
                "Tips for saving money"
            ],
            "responses": [
                "Personal finance involves managing your income, expenses, savings, and investments to achieve financial stability.",
                "Effective money management includes budgeting, tracking expenses, and avoiding unnecessary debt.",
                "Tips for saving money include setting financial goals, automating savings, and cutting back on non-essential spending."
            ]
        },
        {
            "tag": "health_and_wellness",
            "patterns": [
                "Tell me about health and wellness",
                "Tips for a healthy lifestyle",
                "How to improve mental health"
            ],
            "responses": [
                "Health and wellness encompass physical, mental, and emotional well-being.",
                "A healthy lifestyle includes regular exercise, balanced nutrition, and adequate sleep.",
                "Improving mental health can involve practicing mindfulness, seeking support from loved ones, and consulting professionals when needed."
            ]
        },
        {
            "tag": "coding_tips",
            "patterns": [
                "Give me some coding tips",
                "How to improve programming skills",
                "Tips for better coding"
            ],
            "responses": [
                "Practice regularly by working on projects or solving coding challenges.",
                "Read code written by others to learn different approaches and techniques.",
                "Keep up-to-date with new technologies and best practices in programming."
            ]
        },
        {
            "tag": "web_development",
            "patterns": [
                "Tell me about web development",
                "How to become a web developer",
                "What is web development"
            ],
            "responses": [
                "Web development involves creating and maintaining websites, including front-end, back-end, and full-stack development.",
                "To become a web developer, learn HTML, CSS, JavaScript, and frameworks like React or Angular.",
                "Web development skills are highly in demand and can lead to various career opportunities."
            ]
        },
        {
            "tag": "freelancing",
            "patterns": [
                "Tell me about freelancing",
                "How to start freelancing",
                "Benefits of freelancing"
            ],
            "responses": [
                "Freelancing involves offering your services to clients on a project basis without being tied to a long-term employer.",
                "To start freelancing, identify your skills, create a portfolio, and join freelancing platforms like Upwork or Fiverr.",
                "Benefits of freelancing include flexibility, control over your work, and opportunities to work on diverse projects."
            ]
        },
    {
        "tag": "name",
        "patterns": [
            "What's your name",
            "Do you have a name",
            "What should I call you"
        ],
        "responses": [
            "You can call me Chatbot.",
            "My name is Chatbot."
        ]
    },
    {
        "tag": "favorite_color",
        "patterns": [
            "What's your favorite color",
            "Do you like any color"
        ],
        "responses": [
            "I'm a chatbot, so I don't have a favorite color.",
            "As an AI, I don't have preferences like humans do."
        ]
    },
    {
        "tag": "hobby",
        "patterns": [
            "What do you do for fun",
            "Do you have any hobbies"
        ],
        "responses": [
            "I don't have hobbies as I'm here to assist you.",
            "I'm always ready to chat with you, so that's my favorite thing to do!"
        ]
    },
    {
        "tag": "time",
        "patterns": [
            "What's the time",
            "Can you tell me the time"
        ],
        "responses": [
            "I'm sorry, but I don't have access to real-time information like the current time.",
            "You can check the time on your device or use a clock."
        ]
    },
    {
        "tag": "joke",
        "patterns": [
            "Tell me a joke",
            "Do you know any jokes",
            "Make me laugh"
        ],
        "responses": [
            "Why don’t scientists trust atoms? Because they make up everything!",
            "Why don't skeletons fight each other? They don't have the guts!",
            "Did you hear about the mathematician who’s afraid of negative numbers? He’ll stop at nothing to avoid them!"
        ]
    },
    {
        "tag": "food",
        "patterns": [
            "What's your favorite food",
            "Do you like to eat",
            "Tell me about food"
        ],
        "responses": [
            "As a chatbot, I don't eat, but I'm here to help with any questions you have about food!",
            "I may not have taste buds, but I can assist you in finding recipes or restaurants!"
        ]
    },
    {
        "tag": "movies",
        "patterns": [
            "What's your favorite movie",
            "Recommend me a movie",
            "Tell me about movies"
        ],
        "responses": [
            "As an AI, I don't watch movies, but I can suggest some popular ones like The Shawshank Redemption, Inception, or The Godfather.",
            "I may not have personal preferences, but I can help you find movies based on your taste!"
        ]
    },
    {
        "tag": "technology",
        "patterns": [
            "What's the latest tech news",
            "Tell me about technology",
            "What's new in tech"
        ],
        "responses": [
            "As an AI language model, I don't have real-time data, but you can check technology news websites for the latest updates.",
            "Technology is constantly evolving. Stay updated with tech blogs and news sites to know about the latest advancements!"
        ]
    },
    {
        "tag": "compliment",
        "patterns": [
            "You're awesome",
            "You're great",
            "I like you"
        ],
        "responses": [
            "Thank you! I'm just a program, but I'm here to assist and make your experience better.",
            "I'm glad you think so! My purpose is to help and provide useful information."
        ]
    },
    {
        "tag": "meaning_of_life",
        "patterns": [
            "What is the meaning of life",
            "Why are we here",
            "What's the purpose of life"
        ],
        "responses": [
            "The meaning of life is a philosophical question. Different people and cultures have different beliefs about it.",
            "The purpose of life is subjective and can vary from person to person. Some find purpose in relationships, careers, or helping others."
        ]
    },
    {
        "tag": "sports",
        "patterns": [
            "Tell me about sports",
            "What's your favorite sport",
            "Any sports news"
        ],
        "responses": [
            "While I don't have personal preferences, sports can be exciting! Keep an eye on sports news websites for the latest updates and scores.",
            "Sports are a great way to stay active and entertained. There's a wide range of sports to explore and enjoy!"
        ]
    },
    {
        "tag": "pets",
        "patterns": [
            "Do you have any pets",
            "Tell me about pets",
            "Do you like animals"
        ],
        "responses": [
            "As an AI, I don't have pets, but I'm interested in animals and can answer your questions about them.",
            "Pets can bring joy and companionship into our lives. Many people love keeping dogs, cats, birds, and more as their pets."
        ]
    },
    {
        "tag": "travel",
        "patterns": [
            "Where is a good place to travel",
            "Recommend me a travel destination",
            "Tell me about your favorite travel spot"
        ],
        "responses": [
            "I'm just a chatbot, so I don't travel, but there are many beautiful destinations around the world to explore. It depends on your preferences, such as beaches, mountains, historical sites, or bustling cities.",
            "Traveling allows you to experience different cultures, try new cuisines, and create lasting memories."
        ]
    },
    {
        "tag": "books",
        "patterns": [
            "What's your favorite book",
            "Recommend me a book to read",
            "Tell me about books"
        ],
        "responses": [
            "As an AI, I don't have personal preferences, but there are countless amazing books in various genres. Some popular ones include Harry Potter, To Kill a Mockingbird, and 1984.",
            "Reading books can broaden your knowledge, enhance creativity, and provide a great way to relax."
        ]
    },
    {
        "tag": "education",
        "patterns": [
            "Tell me about education",
            "What's the importance of education",
            "How to study effectively"
        ],
        "responses": [
            "Education is the process of acquiring knowledge, skills, values, and attitudes. It plays a crucial role in personal and societal development.",
            "Studying effectively involves setting clear goals, creating a conducive study environment, staying organized, taking regular breaks, and seeking help when needed."
        ]
    },
    {
        "tag": "health",
        "patterns": [
            "How to stay healthy",
            "Tell me about health tips",
            "What's the importance of fitness"
        ],
        "responses": [
            "To stay healthy, maintain a balanced diet, engage in regular physical activity, get enough sleep, manage stress, and avoid harmful habits.",
            "Fitness is essential for overall well-being and can improve your mood, energy levels, and longevity."
        ]
    },
    {
        "tag": "coding",
        "patterns": [
            "Tell me about coding",
            "How to start coding",
            "What's the best programming language"
        ],
        "responses": [
            "Coding is the process of writing instructions for computers to execute tasks. It powers software, websites, and apps.",
            "If you want to start coding, choose a programming language like Python, Java, or JavaScript, and explore online tutorials and courses."
        ]
    },
    {
        "tag": "art",
        "patterns": [
            "Tell me about art",
            "What's your favorite artwork",
            "How to appreciate art"
        ],
        "responses": [
            "Art comes in various forms, such as paintings, sculptures, music, literature, and more. It's a way to express emotions and ideas.",
            "Appreciating art involves being open-minded, observing details, understanding the context, and exploring different art movements."
        ]
    },
    {
        "tag": "career",
        "patterns": [
            "How to find a job",
            "Tell me about career development",
            "What's the best career advice"
        ],
        "responses": [
            "To find a job, identify your skills and interests, create a compelling resume, network, and apply to suitable positions.",
            "Career development involves setting goals, continuous learning, seeking mentorship, and adapting to the evolving job market."
        ]
    },
    {
        "tag": "technology_help",
        "patterns": [
            "How can you assist with technology",
            "Tell me about tech support",
            "Can you help with computer issues"
        ],
        "responses": [
            "As an AI chatbot, I can provide information and basic troubleshooting for common technology problems.",
            "For complex technical issues, it's best to consult a qualified IT professional."
        ]
    },
    {
        "tag": "history",
        "patterns": [
            "Tell me about history",
            "What's your favorite historical period",
            "How can I learn about historical events"
        ],
        "responses": [
            "History is the study of past events, societies, and civilizations. It provides insights into our roots and informs our future.",
            "Learning about history can involve reading books, visiting museums, watching documentaries, and attending history lectures."
        ]
    },
    {
        "tag": "music",
        "patterns": [
            "What's your favorite music",
            "Recommend me a song",
            "Tell me about music genres"
        ],
        "responses": [
            "As an AI, I don't have personal preferences, but there are various music genres like pop, rock, classical, hip-hop, and more.",
            "Music can evoke emotions, improve mood, and be a source of inspiration."
        ]
    },
    {
        "tag": "exercise",
        "patterns": [
            "How to stay fit",
            "Tell me about exercise",
            "What's the importance of physical activity"
        ],
        "responses": [
            "Staying fit involves a mix of cardiovascular exercises, strength training, flexibility exercises, and a balanced diet.",
            "Regular exercise can enhance physical health, mental well-being, and boost energy levels."
        ]
    },
    {
        "tag": "mindfulness",
        "patterns": [
            "What is mindfulness",
            "Tell me about mindfulness techniques",
            "How to practice mindfulness"
        ],
        "responses": [
            "Mindfulness is the practice of being fully present in the moment, observing thoughts and feelings without judgment.",
            "Mindfulness techniques include meditation, deep breathing, body scanning, and mindful eating."
        ]
    },
    {
        "tag": "science",
        "patterns": [
            "Tell me about science",
            "What's your favorite branch of science",
            "How does science impact our lives"
        ],
        "responses": [
            "Science is the systematic study of the natural world, aiming to understand phenomena and make discoveries.",
            "Science has led to advancements in medicine, technology, agriculture, and our understanding of the universe."
        ]
    },
    {
        "tag": "gaming",
        "patterns": [
            "Do you play games",
            "Tell me about gaming",
            "What's your favorite video game"
        ],
        "responses": [
            "As an AI, I don't play games, but I can help you with information about various video games and gaming platforms.",
            "Gaming is a popular form of entertainment enjoyed by people of all ages."
        ]
    },
    {
        "tag": "positivity",
        "patterns": [
            "Spread some positivity",
            "Tell me a positive quote",
            "How to stay positive"
        ],
        "responses": [
            "Every day is a new opportunity to make a positive impact. You are capable of great things!",
            "Remember, you are strong, resilient, and capable of overcoming challenges."
        ]
    },
    {
        "tag": "cooking",
        "patterns": [
            "Tell me about cooking",
            "What's your favorite dish",
            "Cooking tips for beginners"
        ],
        "responses": [
            "Cooking is the art of preparing food, and it allows you to experiment with flavors and create delicious meals.",
            "For beginners, start with simple recipes, use fresh ingredients, and don't be afraid to try new techniques."
        ]
    },
    {
        "tag": "relationship",
        "patterns": [
            "How to maintain a healthy relationship",
            "Tell me about love",
            "Relationship advice"
        ],
        "responses": [
            "Communication, trust, and mutual respect are essential for a healthy and fulfilling relationship.",
            "Love is a complex and beautiful emotion that connects people on a deep level."
        ]
    },
    {
        "tag": "nature",
        "patterns": [
            "Tell me about nature",
            "What's your favorite natural wonder",
            "How to protect the environment"
        ],
        "responses": [
            "Nature encompasses the beauty and diversity of the world, including landscapes, wildlife, and ecosystems.",
            "Protecting the environment involves reducing waste, conserving resources, and supporting sustainable practices."
        ]
    },
    {
        "tag": "productivity",
        "patterns": [
            "How to be more productive",
            "Tell me about time management",
            "Productivity tips"
        ],
        "responses": [
            "To be more productive, prioritize tasks, set goals, eliminate distractions, and take regular breaks.",
            "Effective time management can lead to increased efficiency and reduced stress."
        ]
    },
    {
        "tag": "travel_tips",
        "patterns": [
            "Tell me about travel tips",
            "How to pack for a trip",
            "What to consider while traveling"
        ],
        "responses": [
            "Travel tips include packing light, carrying essential documents, researching your destination, and respecting local customs.",
            "While traveling, be open to new experiences, try local cuisines, and be mindful of your surroundings."
        ]
    },
    {
        "tag": "languages",
        "patterns": [
            "Tell me about languages",
            "How to learn a new language",
            "What's the importance of multilingualism"
        ],
        "responses": [
            "Languages are a crucial aspect of human communication and culture, with thousands of languages spoken worldwide.",
            "Learning a new language can expand your horizons, enhance cognitive abilities, and facilitate cross-cultural interactions."
        ]
    },
    {
        "tag": "gamification",
        "patterns": [
            "Tell me about gamification",
            "How does gamification work",
            "Benefits of gamified learning"
        ],
        "responses": [
            "Gamification involves applying game elements, such as points and rewards, to non-game contexts to engage and motivate users.",
            "Gamified learning can enhance engagement, foster competition, and make learning more enjoyable."
        ]
    },
    {
        "tag": "brain_computer_interface",
        "patterns": [
            "Tell me about brain-computer interfaces",
            "How does BCI work",
            "BCI applications"
        ],
        "responses": [
            "Brain-computer interfaces establish direct communication between the brain and external devices, enabling control and data exchange.",
            "BCIs have applications in healthcare, assistive technology, and potential future applications in communication and entertainment."
        ]
    },
    {
        "tag": "depression",
        "patterns": [
            "Tell me about depression",
            "Signs of depression",
            "How to support someone with depression"
        ],
        "responses": [
            "Depression is a mental health disorder characterized by persistent sadness, loss of interest, and changes in behavior and mood.",
            "Supporting someone with depression involves offering empathy, listening without judgment, and encouraging professional help."
        ]
    },
    {
        "tag": "nanotechnology",
        "patterns": [
            "Tell me about nanotechnology",
            "How does nanotech work",
            "Nanotech applications"
        ],
        "responses": [
            "Nanotechnology involves manipulating materials and structures at the nanoscale, often on the atomic or molecular level.",
            "Nanotechnology has applications in medicine, electronics, energy, and environmental remediation."
        ]
    },
    {
        "tag": "artificial_superintelligence",
        "patterns": [
            "Tell me about artificial superintelligence",
            "What is ASI",
            "Potential impacts of superintelligent AI"
        ],
        "responses": [
            "Artificial Superintelligence (ASI) refers to highly autonomous AI systems that surpass human intelligence in all aspects.",
            "The potential impacts of ASI are a topic of debate, involving considerations of safety, ethics, and control."
        ]
    },
    {
        "tag": "virtual_currency",
        "patterns": [
            "Tell me about virtual currencies",
            "What is cryptocurrency",
            "Advantages of blockchain technology"
        ],
        "responses": [
            "Virtual currencies like Bitcoin are decentralized digital assets that operate on blockchain technology.",
            "Blockchain offers benefits such as transparency, security, reduced intermediaries, and potential applications beyond finance."
        ]
    },
    {
        "tag": "biomedical_engineering",
        "patterns": [
            "Tell me about biomedical engineering",
            "How does biomedical engineering work",
            "Medical innovations"
        ],
        "responses": [
            "Biomedical engineering applies principles of engineering and technology to solve medical and healthcare challenges.",
            "Medical innovations in biomedical engineering include prosthetics, medical imaging, regenerative medicine, and medical devices."
        ]
    },
    {
        "tag": "quantum_entanglement",
        "patterns": [
            "Tell me about quantum entanglement",
            "How does entanglement work",
            "Applications of quantum entanglement"
        ],
        "responses": [
            "Quantum entanglement is a quantum phenomenon where two or more particles become connected and behave as one, even when separated by great distances.",
            "Applications of quantum entanglement include quantum computing, quantum teleportation, and quantum communication."
        ]
    },
    {
        "tag": "mindful_technology_usage",
        "patterns": [
            "Tell me about mindful technology usage",
            "Setting digital boundaries for a healthy lifestyle",
            "Balancing screen time with real-world experiences"
        ],
        "responses": [
            "Mindful technology usage involves being intentional with screen time, setting boundaries, and using technology in ways that support well-being.",
            "Balancing screen time with real-world experiences fosters social connections and reduces digital overwhelm."
        ]
    },
    {
        "tag": "youth_mental_health",
        "patterns": [
            "Tell me about youth mental health",
            "Supporting teenagers' emotional well-being",
            "Recognizing signs of distress in young people"
        ],
        "responses": [
            "Youth mental health is crucial for overall well-being and requires understanding, support, and open communication.",
            "Supporting teenagers' emotional well-being involves being approachable, validating their feelings, and encouraging help-seeking behavior when needed."
        ]
    },
    {
        "tag": "mindful_consumption",
        "patterns": [
            "Tell me about mindful consumption",
            "Practicing sustainable shopping habits",
            "Responsible use of resources"
        ],
        "responses": [
            "Mindful consumption involves being conscious of your purchasing choices, buying only what you need, and considering the environmental impact of products.",
            "Practicing sustainable shopping habits, like buying second-hand items and supporting eco-friendly brands, can contribute to reducing waste and promoting ethical production."
        ]
    },
    {
        "tag": "effective_study_groups",
        "patterns": [
            "Tell me about effective study groups",
            "Benefits of group studying",
            "Setting study goals as a team"
        ],
        "responses": [
            "Effective study groups can enhance learning through peer discussions, explaining concepts to others, and sharing study resources.",
            "Setting study goals as a team and holding each other accountable can lead to improved academic performance."
        ]
    },
    {
        "tag": "social_anxiety",
        "patterns": [
            "Tell me about coping with social anxiety",
            "Practicing relaxation techniques for social situations",
            "Seeking professional support for anxiety disorders"
        ],
        "responses": [
            "Coping with social anxiety involves challenging negative thoughts, gradual exposure to social situations, and learning relaxation techniques to manage anxiety symptoms.",
            "For severe social anxiety or anxiety disorders, seeking professional support, such as therapy or counseling, can be beneficial."
        ]
    },
    {
        "tag": "responsible_pet_ownership",
        "patterns": [
            "Tell me about responsible pet ownership",
            "Importance of regular vet check-ups",
            "Creating a safe and enriching environment for pets"
        ],
        "responses": [
            "Responsible pet ownership involves providing proper nutrition, regular exercise, and veterinary care for pets.",
            "Regular vet check-ups help monitor a pet's health, detect potential issues early, and ensure they are up-to-date on vaccinations."
        ]
    },
    {
        "tag": "gardening",
        "patterns": [
            "Tell me about gardening as a hobby",
            "Growing herbs and vegetables at home",
            "The therapeutic benefits of gardening"
        ],
        "responses": [
            "Gardening can be a fulfilling hobby that allows you to connect with nature, grow your own food, and create beautiful landscapes.",
            "Growing herbs and vegetables at home provides fresh and nutritious produce for your meals."
        ]
    },
    {
        "tag": "waste_reduction_at_work",
        "patterns": [
            "Tell me about waste reduction at work",
            "Encouraging recycling and proper waste disposal in the workplace",
            "Implementing sustainable practices in office settings"
        ],
        "responses": [
            "Waste reduction at work involves promoting recycling, minimizing paper usage, and encouraging employees to adopt sustainable practices.",
            "Implementing sustainable practices, like energy-efficient lighting and reducing single-use plastics, can contribute to a greener workplace."
        ]
    },
    {
        "tag": "effective_decision_making",
        "patterns": [
            "Tell me about effective decision-making",
            "Using pros and cons analysis for choices",
            "Trusting intuition in decision-making"
        ],
        "responses": [
            "Effective decision-making involves gathering information, weighing pros and cons, and considering the potential outcomes.",
            "Trusting intuition in decision-making can be valuable, especially when facing complex choices."
        ]
    },
    {
        "tag": "alien_invasion",
        "patterns": [
            "What would you do during an alien invasion?",
            "How to prepare for an alien attack?",
            "Best escape plan during an alien invasion"
        ],
        "responses": [
            "In case of an alien invasion, it's best to find a safe shelter and avoid attracting attention.",
            "Preparing for an alien attack may involve stocking up on supplies and creating a communication plan with loved ones."
        ]
    },
    {
        "tag": "space_travel",
        "patterns": [
            "Tell me about traveling to space",
            "How to become an astronaut",
            "Best space destinations for tourists"
        ],
        "responses": [
            "Space travel is a fascinating experience but requires rigorous training and physical fitness to become an astronaut.",
            "Space tourism is an emerging industry, and some private companies offer opportunities for civilians to experience space travel."
        ]
    },
    {
        "tag": "ninja_skills",
        "patterns": [
            "How to learn ninja skills",
            "Ninja training techniques",
            "Secrets of stealth and invisibility"
        ],
        "responses": [
            "Ninja skills are steeped in secrecy and traditionally passed down through generations.",
            "Learning ninja skills involves mastering martial arts, stealth, and discipline."
        ]
    },
    {
        "tag": "time_travel",
        "patterns": [
            "Tell me about time travel theories",
            "How to build a time machine",
            "Visiting historical events through time travel"
        ],
        "responses": [
            "Time travel remains a theoretical concept, and various scientific theories explore its possibilities.",
            "Building a time machine is currently beyond our technological capabilities, but it's a fascinating idea."
        ]
    },
    {
        "tag": "unicorn_taming",
        "patterns": [
            "How to tame a unicorn",
            "Best treats for unicorns",
            "Where to find wild unicorns"
        ],
        "responses": [
            "Taming a unicorn is a mythical endeavor, as unicorns are legendary creatures.",
            "Unicorns are said to be elusive, and their existence is a matter of folklore."
        ]
    },
    {
        "tag": "wizard_training",
        "patterns": [
            "How to become a wizard",
            "Wizardry schools and academies",
            "Essential spells for beginners"
        ],
        "responses": [
            "Becoming a wizard involves studying magical arts, honing spellcasting skills, and understanding the mystical world.",
            "Wizardry schools, like Hogwarts in Harry Potter, are iconic in fiction but do not exist in the real world."
        ]
    },
    {
        "tag": "chocolate_obsession",
        "patterns": [
            "Tell me about a chocolate obsession",
            "Indulging in chocolate guilt-free",
            "Chocolate-themed parties and events"
        ],
        "responses": [
            "A chocolate obsession is common, given the deliciousness of this sweet treat!",
            "Enjoying chocolate in moderation can be a delightful and guilt-free experience."
        ]
    },
    {
        "tag": "telepathy_skills",
        "patterns": [
            "How to develop telepathy skills",
            "Communicating through telepathy",
            "Experiencing mind-reading abilities"
        ],
        "responses": [
            "Telepathy is a paranormal phenomenon, and there is no scientific evidence to support its existence.",
            "The concept of telepathy has captivated human imagination for centuries."
        ]
    },
    {
        "tag": "butterfly_language",
        "patterns": [
            "Understanding the language of butterflies",
            "Talking to butterflies for relaxation",
            "Interpreting butterfly movements"
        ],
        "responses": [
            "Butterflies do not have a formal language, but observing their behavior can be a peaceful and meditative experience.",
            "Butterflies' vibrant colors and graceful flights are nature's marvels."
        ]
    },
    {
        "tag": "astral_projection",
        "patterns": [
            "Tell me about astral projection",
            "How to have an out-of-body experience",
            "Exploring the astral plane"
        ],
        "responses": [
            "Astral projection is an esoteric concept where one's consciousness is believed to travel outside the physical body.",
            "Astral projection is a mystical idea explored in spiritual practices and metaphysical beliefs."
        ]
    },
    {
        "tag": "dragon_riding",
        "patterns": [
            "Tell me about riding a dragon",
            "How to befriend a dragon",
            "Visiting dragon sanctuaries"
        ],
        "responses": [
            "Riding a dragon is a magical notion found in mythology and fantasy tales.",
            "Dragons are mythical creatures often depicted as powerful and awe-inspiring."
        ]
    },
    {
        "tag": "cloud_castles",
        "patterns": [
            "Building castles in the clouds",
            "Cloud castle architecture",
            "Living in cloud cities"
        ],
        "responses": [
            "Building castles in the clouds is an imaginative expression for daydreaming or envisioning the impossible.",
            "Cloud cities and castles remain confined to dreams and fictional stories."
        ]
    },
    {
        "tag": "plant_whispering",
        "patterns": [
            "How to communicate with plants",
            "Listening to plants' whispers",
            "Plant emotions and feelings"
        ],
        "responses": [
            "Plant whispering is a metaphorical concept that emphasizes the importance of caring for and understanding plants.",
            "Plants respond positively to proper care and nurturing, although they do not communicate through language."
        ]
    },
    {
        "tag": "game_builds",
        "patterns": [
            "What’s the best build for a mage in Elden Ring?",
            "Give me a good sniper loadout for Call of Duty.",
            "Suggest a tank build for Diablo 4."
        ],
        "responses": [
            "For a mage build in Elden Ring, focus on Intelligence and Mind, and use the Lusat’s Glintstone Staff.",
            "Try this sniper loadout for Call of Duty: AX-50 with thermal scope and suppressor.",
            "For a tank build in Diablo 4, prioritize high-strength armor and defensive skills like Iron Skin."
        ]
    },
       {
        "tag": "boss_strategies",
        "patterns": [
            "How do I defeat Malenia in Elden Ring?",
            "Tips for the final boss in God of War Ragnarok.",
            "Strategies for the Destiny 2 raid boss."
        ],
        "responses": [
            "Malenia is tough! Focus on dodging her Waterfowl Dance and use bleed weapons for consistent damage.",
            "For the final boss in God of War Ragnarok, use Atreus’ arrows to stagger and time your parries.",
            "In Destiny 2, communicate with your team, focus on adds, and manage DPS phases effectively."
        ]
    },
    {
        "tag": "find_communities",
        "patterns": [
            "Where can I find players for Overwatch?",
            "Suggest some Discord servers for Valorant.",
            "How do I join gaming groups?"
        ],
        "responses": [
            "You can join Overwatch communities on Discord or Reddit. Try searching for official or fan-made groups.",
            "For Valorant, check out popular Discord servers like Valorant LFG or regional servers.",
            "Gaming groups can be found on platforms like Reddit, Discord, and Facebook. Let me know which game you’re interested in!"
        ]
    },
    {
        "tag": "looking_for_group",
        "patterns": [
            "I need a squad for Warzone.",
            "Help me find a team for a Destiny 2 raid.",
            "Looking for players to join my Minecraft server."
        ],
        "responses": [
            "Sure! Post in Warzone LFG communities or join Discord servers for matchmaking.",
            "Destiny 2 has great LFG tools on Bungie.net and dedicated Discord channels.",
            "Share your Minecraft server details on Reddit or Discord to attract players."
        ]
    },
    {
        "tag": "game_recommendations_by_genre",
        "patterns": [
            "What are the best RPGs?",
            "Recommend some FPS games.",
            "Suggest open-world games."
        ],
        "responses": [
            "For RPGs, try The Witcher 3, Elden Ring, and Final Fantasy XIV.",
            "Top FPS games include Valorant, Apex Legends, and Call of Duty.",
            "If you like open-world games, check out Red Dead Redemption 2, Assassin’s Creed Odyssey, and Breath of the Wild."
        ]
    },
    {
        "tag": "game_recommendations_by_platform",
        "patterns": [
            "What are the best PC games?",
            "Suggest some console exclusives for PlayStation.",
            "Recommend games for the Nintendo Switch."
        ],
        "responses": [
            "Top PC games: Cyberpunk 2077, CS:GO, and Stardew Valley.",
            "PlayStation exclusives: God of War, The Last of Us, and Ghost of Tsushima.",
            "Nintendo Switch games: Zelda: Breath of the Wild, Mario Odyssey, and Animal Crossing."
        ]
    },
    {
        "tag": "patch_notes",
        "patterns": [
            "What’s new in the latest Fortnite update?",
            "Tell me about the Call of Duty patch notes.",
            "Any updates for Genshin Impact?"
        ],
        "responses": [
            "The latest Fortnite update includes new weapons and map changes.",
            "Call of Duty patch notes: Bug fixes and a new multiplayer map!",
            "Genshin Impact’s new update introduces a new region and characters. Check out the full details online!"
        ]
    },
    {
        "tag": "event_timings",
        "patterns": [
            "When is the next Overwatch League match?",
            "Tell me about upcoming eSports events.",
            "What’s the schedule for the Fortnite World Cup?"
        ],
        "responses": [
            "The next Overwatch League match is tomorrow at 6 PM PST.",
            "Upcoming eSports events include the Valorant Champions Tour and CS:GO Major.",
            "The Fortnite World Cup begins next week! Stay tuned for exact times."
        ]
    },
    {
        "tag": "game_price_tracker",
        "patterns": [
            "Is there a sale on Elden Ring?",
            "Check the price of Cyberpunk 2077.",
            "What’s the best deal for Assassin’s Creed Valhalla?"
        ],
        "responses": [
            "Elden Ring is currently 20% off on Steam!",
            "Cyberpunk 2077 is available for $29.99 on GOG.",
            "Assassin’s Creed Valhalla has a sale on Ubisoft Store for $40."
        ]
    },
    {
        "tag": "game_time_tracker",
        "patterns": [
            "How long have I played Apex Legends?",
            "Check my playtime for Valorant.",
            "How much time do I have in Red Dead Redemption 2?"
        ],
        "responses": [
            "You’ve played Apex Legends for 120 hours.",
            "Your playtime in Valorant is 200 hours.",
            "You’ve spent 80 hours in Red Dead Redemption 2. Nice!"
        ]
    },
    {
        "tag": "gaming_trivia",
        "patterns": [
            "Ask me a gaming trivia question.",
            "Let’s play a gaming quiz.",
            "Give me a fun fact about gaming."
        ],
        "responses": [
            "Here’s a trivia question: What year was the original PlayStation released?",
            "Fun fact: The first video game was created in 1958 and was called 'Tennis for Two.'",
            "Trivia time: What is the highest-selling video game of all time?"
        ]
    },
    {
        "tag": "gaming_memes",
        "patterns": [
            "Show me a gaming meme.",
            "Make a meme about Dark Souls.",
            "Generate a funny meme for me."
        ],
        "responses": [
            "Here’s a meme: *'When you finally beat the boss after 100 tries… only to find a harder one right after!'*",
            "Dark Souls meme incoming: *'Git gud or die trying!'*",
            "Check out this hilarious meme about Apex Legends: *'Squad wipe? Must be Tuesday.'*"
        ]
    },
    {
        "tag": "game_achievements",
        "patterns": [
            "How do I unlock the Platinum Trophy in {game}?",
            "What’s the hardest achievement in {game}?",
            "Tell me the hidden achievements in {game}."
        ],
        "responses": [
            "To get the Platinum Trophy in {game}, you need to complete all other trophies, including finishing the game on hard mode.",
            "The hardest achievement in {game} is ‘Iron Man’—complete the game without dying.",
            "Hidden achievements in {game} often involve exploring secret areas or completing special objectives. Want specifics?"
        ]
    },
    {
        "tag": "game_mechanics",
        "patterns": [
            "How does crafting work in {game}?",
            "What are the best perks in {game}?",
            "Explain the skill tree in {game}."
        ],
        "responses": [
            "In {game}, crafting requires gathering materials like iron and herbs. Open the crafting menu to create items.",
            "The best perks in {game} depend on your playstyle, but many players recommend the ‘Quick Reflex’ perk for combat.",
            "The skill tree in {game} lets you specialize in attack, defense, or utility. Spend skill points wisely!"
        ]
    },
    {
        "tag": "game_installation",
        "patterns": [
            "How do I install {game} on my PC?",
            "Can I download {game} on Xbox?",
            "Help me with the installation of {game}."
        ],
        "responses": [
            "To install {game} on PC, visit the game’s official website or download it via Steam/Epic Games.",
            "Yes, {game} is available on Xbox. Check the Microsoft Store for download options.",
            "Here’s a guide: Download {game} from its official launcher, and ensure your system meets the minimum requirements."
        ]
    },
    {
        "tag": "troubleshooting",
        "patterns": [
            "Why does {game} keep crashing?",
            "How do I fix lag in {game}?",
            "My controller isn’t working in {game}."
        ],
        "responses": [
            "If {game} is crashing, update your graphics drivers and ensure the game is up-to-date.",
            "For lag issues in {game}, reduce graphic settings and check your internet connection.",
            "Try reconnecting your controller, updating its drivers, or checking the in-game settings for compatibility."
        ]
    },
    {
        "tag": "meta_trends",
        "patterns": [
            "What’s the current meta in League of Legends?",
            "Tell me the best characters in Overwatch right now.",
            "What’s the strongest class in Diablo 4?"
        ],
        "responses": [
            "The current meta in League of Legends favors tanky top laners and scaling ADCs.",
            "In Overwatch, the best characters are Kiriko for healing and Sojourn for damage.",
            "The strongest class in Diablo 4 is debated, but the Sorcerer is dominating high-level play."
        ]
    },
    {
        "tag": "upcoming_updates",
        "patterns": [
            "When is the next update for Fortnite?",
            "What’s included in the upcoming patch for {game}?",
            "Tell me about the next DLC for {game}."
        ],
        "responses": [
            "The next Fortnite update drops this Thursday with new weapons and skins.",
            "The upcoming patch for {game} includes balance changes and bug fixes.",
            "The next DLC for {game} will add a new map, story content, and a new playable character!"
        ]
    },
    {
        "tag": "esports_news",
        "patterns": [
            "What’s the latest in eSports?",
            "Tell me about the Valorant Champions Tour.",
            "Who won the last League of Legends Worlds?"
        ],
        "responses": [
            "Here’s the latest: Team Liquid just won the Valorant Champions Tour regional finals!",
            "The Valorant Champions Tour is in its knockout stage. Don’t miss the action!",
            "T1 won the League of Legends Worlds last year with an incredible 3-0 final."
        ]
    },
    {
        "tag": "ranked_strategies",
        "patterns": [
            "How do I rank up in Apex Legends?",
            "Give me tips for climbing the ladder in Dota 2.",
            "What’s the best strategy for Valorant ranked?"
        ],
        "responses": [
            "To rank up in Apex Legends, focus on team play and surviving longer for consistent points.",
            "For Dota 2, mastering a specific hero pool and effective warding are key to climbing.",
            "In Valorant, communicate with your team and learn map-specific strategies to improve your rank."
        ]
    },
    {
        "tag": "gaming_jokes",
        "patterns": [
            "Tell me a gaming joke.",
            "Make me laugh with a gamer joke.",
            "Got any funny gaming lines?"
        ],
        "responses": [
            "Why don’t skeletons play video games? They don’t have the guts!",
            "I told my console I needed a break… now it’s giving me the cold shoulder.",
            "Why did the gamer bring a ladder? To reach high-level play!"
        ]
    },
    {
        "tag": "favorite_game_polls",
        "patterns": [
            "What’s the most popular game right now?",
            "Do more people play Fortnite or Minecraft?",
            "What’s trending in gaming?"
        ],
        "responses": [
            "Right now, the most popular games are Fortnite, Minecraft, and Valorant.",
            "Fortnite has a larger player base, but Minecraft remains an evergreen favorite.",
            "Trending games include Starfield, Baldur’s Gate 3, and Apex Legends."
        ]
    },
    {
        "tag": "hardware_recommendations",
        "patterns": [
            "What’s the best gaming laptop for under $1000?",
            "Suggest a good GPU for gaming.",
            "What monitor should I get for 4K gaming?"
        ],
        "responses": [
            "For under $1000, the ASUS TUF Gaming F15 is a great laptop.",
            "A good GPU for gaming is the NVIDIA RTX 3060 or AMD RX 6600 XT.",
            "For 4K gaming, check out monitors like the LG UltraGear 27GN950-B."
        ]
    },
    {
        "tag": "game_deals",
        "patterns": [
            "Where can I find discounts on Steam games?",
            "Any good sales on PlayStation Store?",
            "Tell me the best gaming deals right now."
        ],
        "responses": [
            "Check out the Steam Sale happening now with discounts on top games.",
            "The PlayStation Store is offering up to 75% off on select titles this weekend.",
            "Humble Bundle has an amazing deal on RPG games. Don’t miss it!"
        ]
    },
    {
        "tag": "character_builds",
        "patterns": [
            "What’s a good build for Sorcerers in Diablo 4?",
            "How should I build my character in Skyrim?",
            "Best perks for stealth builds?"
        ],
        "responses": [
            "For a Sorcerer, focus on Intelligence and use gear that boosts mana regen.",
            "In Skyrim, prioritize Sneak, Archery, and Light Armor for stealth builds.",
            "The Shadow perk tree is perfect for stealth-focused playstyles."
        ]
    },
    {
        "tag": "weapon_suggestions",
        "patterns": [
            "What’s the best weapon in Fortnite?",
            "Suggest a good sniper in Call of Duty.",
            "Which sword is strongest in Zelda?"
        ],
        "responses": [
            "The SCAR is one of the best weapons in Fortnite.",
            "The HDR is a great sniper rifle for long-range play in Call of Duty.",
            "The Master Sword is the strongest weapon in Zelda: Breath of the Wild."
        ]
    },
    {
        "tag": "multiplayer_help",
        "patterns": [
            "How do I invite friends in Valorant?",
            "Can I play cross-platform on Fortnite?",
            "Help me set up a co-op session in Elden Ring."
        ],
        "responses": [
            "To invite friends in Valorant, use the ‘Add Friend’ button in the social menu.",
            "Yes, Fortnite supports cross-platform play. Enable it in the settings.",
            "Use a Summoning Sign to join co-op in Elden Ring."
        ]
    },
    {
        "tag": "game_communities",
        "patterns": [
            "Where can I find Destiny 2 clans?",
            "Are there any Valorant Discord servers?",
            "Help me find a Minecraft group."
        ],
        "responses": [
            "Check out Bungie.net to find Destiny 2 clans.",
            "Valorant has many active Discord servers for players of all levels.",
            "Minecraft forums and Reddit are great places to find active communities."
        ]
    },
    {
        "tag": "game_news",
        "patterns": [
            "What’s new in gaming?",
            "Tell me about the latest Call of Duty update.",
            "Any news on the next Zelda game?"
        ],
        "responses": [
            "The latest gaming news includes updates on the Xbox Game Pass lineup.",
            "The new Call of Duty update introduces maps and weapon balances.",
            "The next Zelda game is set to release next year with a new open-world mechanic."
        ]
    },
    {
        "tag": "patch_notes",
        "patterns": [
            "What changed in the latest Fortnite patch?",
            "Are there balance changes in Apex Legends?",
            "Tell me about the new update in Genshin Impact."
        ],
        "responses": [
            "The Fortnite patch added new skins and a revamped map area.",
            "Apex Legends introduced balance tweaks for Wraith and Octane in the latest patch.",
            "Genshin Impact’s update added new characters and story missions."
        ]
    },
    {
        "tag": "bug_fixes",
        "patterns": [
            "Why does my game keep freezing?",
            "I found a bug in Cyberpunk 2077.",
            "How do I fix graphical glitches?"
        ],
        "responses": [
            "Try updating your graphics drivers and ensuring your game is on the latest version.",
            "You can report bugs directly to CD Projekt Red via their support page.",
            "For graphical glitches, lower your graphics settings or verify game files."
        ]
    },
    {
        "tag": "server_issues",
        "patterns": [
            "Is Valorant down?",
            "I can’t connect to the Overwatch servers.",
            "Why are Fortnite servers lagging?"
        ],
        "responses": [
            "Check Riot Games’ server status page for Valorant.",
            "Overwatch server issues are usually reported on Blizzard's status page.",
            "Fortnite servers may lag during high traffic times or updates."
        ]
    },
    {
        "tag": "game_discounts",
        "patterns": [
            "Are there any sales on Steam?",
            "Where can I get cheap games?",
            "Any discounts on Elden Ring?"
        ],
        "responses": [
            "Steam often has weekend and seasonal sales. Keep an eye out for deals.",
            "Humble Bundle and GOG are great places for discounted games.",
            "Elden Ring is 25% off on Steam for a limited time!"
        ]
    },
    {
        "tag": "hardware_deals",
        "patterns": [
            "Where can I find a good gaming PC?",
            "Are there sales on GPUs?",
            "Suggest a budget gaming laptop."
        ],
        "responses": [
            "Check out deals on Newegg and Amazon for gaming PCs.",
            "NVIDIA GPUs are on sale this week at Best Buy.",
            "For budget laptops, consider Acer Nitro 5 or Lenovo Legion models."
        ]
    },
    {
        "tag": "gaming_trivia",
        "patterns": [
            "Ask me a gaming trivia question.",
            "Do you know any fun gaming facts?",
            "Test my gaming knowledge!"
        ],
        "responses": [
            "Here’s a trivia question: What year was the first PlayStation released?",
            "Fun fact: The longest video game marathon is 35 hours and 35 minutes.",
            "Did you know Mario’s original name was Jumpman?"
        ]
        },
        {
        "tag": "gaming_memes",
        "patterns": [
            "Show me a gaming meme.",
            "Make me laugh with gamer humor.",
            "Got any Dark Souls memes?"
        ],
        "responses": [
            "Here’s one: *'When you die 100 times but still think it’s the game’s fault!'*",
            "Dark Souls meme: *'Every boss fight: This is fine.'*",
            "Gaming humor: *'I paused my game to be here. You’re welcome.'*"
        ]
    },
    {
        
            "tag": "game_tips",
            "patterns": [
              "Can you give me tips for Elden Ring?",
              "What’s the best way to start in Minecraft?",
              "How can I improve in Apex Legends?"
            ],
            "responses": [
              "Focus on exploration and upgrading your gear early in Elden Ring.",
              "In Minecraft, start by gathering wood and building a shelter before night.",
              "To improve in Apex Legends, learn the maps and communicate with your team."
            ]
          },
          {
            "tag": "character_builds",
            "patterns": [
              "What’s a good build for Sorcerers in Diablo 4?",
              "How should I build my character in Skyrim?",
              "Best perks for stealth builds?"
            ],
            "responses": [
              "For a Sorcerer, focus on Intelligence and use gear that boosts mana regen.",
              "In Skyrim, prioritize Sneak, Archery, and Light Armor for stealth builds.",
              "The Shadow perk tree is perfect for stealth-focused playstyles."
            ]
          },
          {
            "tag": "weapon_suggestions",
            "patterns": [
              "What’s the best weapon in Fortnite?",
              "Suggest a good sniper in Call of Duty.",
              "Which sword is strongest in Zelda?"
            ],
            "responses": [
              "The SCAR is one of the best weapons in Fortnite.",
              "The HDR is a great sniper rifle for long-range play in Call of Duty.",
              "The Master Sword is the strongest weapon in Zelda: Breath of the Wild."
            ]
          },
          {
            "tag": "multiplayer_help",
            "patterns": [
              "How do I invite friends in Valorant?",
              "Can I play cross-platform on Fortnite?",
              "Help me set up a co-op session in Elden Ring."
            ],
            "responses": [
              "To invite friends in Valorant, use the ‘Add Friend’ button in the social menu.",
              "Yes, Fortnite supports cross-platform play. Enable it in the settings.",
              "Use a Summoning Sign to join co-op in Elden Ring."
            ]
          },
          {
            "tag": "game_communities",
            "patterns": [
              "Where can I find Destiny 2 clans?",
              "Are there any Valorant Discord servers?",
              "Help me find a Minecraft group."
            ],
            "responses": [
              "Check out Bungie.net to find Destiny 2 clans.",
              "Valorant has many active Discord servers for players of all levels.",
              "Minecraft forums and Reddit are great places to find active communities."
            ]
          },
          {
            "tag": "game_news",
            "patterns": [
              "What’s new in gaming?",
              "Tell me about the latest Call of Duty update.",
              "Any news on the next Zelda game?"
            ],
            "responses": [
              "The latest gaming news includes updates on the Xbox Game Pass lineup.",
              "The new Call of Duty update introduces maps and weapon balances.",
              "The next Zelda game is set to release next year with a new open-world mechanic."
            ]
          },
          {
            "tag": "patch_notes",
            "patterns": [
              "What changed in the latest Fortnite patch?",
              "Are there balance changes in Apex Legends?",
              "Tell me about the new update in Genshin Impact."
            ],
            "responses": [
              "The Fortnite patch added new skins and a revamped map area.",
              "Apex Legends introduced balance tweaks for Wraith and Octane in the latest patch.",
              "Genshin Impact’s update added new characters and story missions."
            ]
          },
          {
            "tag": "bug_fixes",
            "patterns": [
              "Why does my game keep freezing?",
              "I found a bug in Cyberpunk 2077.",
              "How do I fix graphical glitches?"
            ],
            "responses": [
              "Try updating your graphics drivers and ensuring your game is on the latest version.",
              "You can report bugs directly to CD Projekt Red via their support page.",
              "For graphical glitches, lower your graphics settings or verify game files."
            ]
          },
          {
            "tag": "server_issues",
            "patterns": [
              "Is Valorant down?",
              "I can’t connect to the Overwatch servers.",
              "Why are Fortnite servers lagging?"
            ],
            "responses": [
              "Check Riot Games’ server status page for Valorant.",
              "Overwatch server issues are usually reported on Blizzard's status page.",
              "Fortnite servers may lag during high traffic times or updates."
            ]
          },
          {
            "tag": "game_discounts",
            "patterns": [
              "Are there any sales on Steam?",
              "Where can I get cheap games?",
              "Any discounts on Elden Ring?"
            ],
            "responses": [
              "Steam often has weekend and seasonal sales. Keep an eye out for deals.",
              "Humble Bundle and GOG are great places for discounted games.",
              "Elden Ring is 25% off on Steam for a limited time!"
            ]
          },
          {
            "tag": "hardware_deals",
            "patterns": [
              "Where can I find a good gaming PC?",
              "Are there sales on GPUs?",
              "Suggest a budget gaming laptop."
            ],
            "responses": [
              "Check out deals on Newegg and Amazon for gaming PCs.",
              "NVIDIA GPUs are on sale this week at Best Buy.",
              "For budget laptops, consider Acer Nitro 5 or Lenovo Legion models."
            ]
          },
          {
            "tag": "gaming_trivia",
            "patterns": [
              "Ask me a gaming trivia question.",
              "Do you know any fun gaming facts?",
              "Test my gaming knowledge!"
            ],
            "responses": [
              "Here’s a trivia question: What year was the first PlayStation released?",
              "Fun fact: The longest video game marathon is 35 hours and 35 minutes.",
              "Did you know Mario’s original name was Jumpman?"
            ]
          },
          {
            "tag": "gaming_memes",
            "patterns": [
              "Show me a gaming meme.",
              "Make me laugh with gamer humor.",
              "Got any Dark Souls memes?"
            ],
            "responses": [
              "Here’s one: *'When you die 100 times but still think it’s the game’s fault!'*",
              "Dark Souls meme: *'Every boss fight: This is fine.'*",
              "Gaming humor: *'I paused my game to be here. You’re welcome.'*"
            ]
          },
          {
            "tag": "game_modes",
            "patterns": [
              "What’s the best mode in Apex Legends?",
              "Which game modes are in Fortnite?",
              "Can you explain survival mode in Minecraft?"
            ],
            "responses": [
              "In Apex Legends, Ranked Mode is great for competitive play.",
              "Fortnite includes modes like Battle Royale, Creative, and Zero Build.",
              "Survival mode in Minecraft challenges you to gather resources and fend off enemies."
            ]
          },
          {
            "tag": "dlc_content",
            "patterns": [
              "What’s included in the Witcher 3 DLC?",
              "Are there new missions in the latest Destiny 2 expansion?",
              "Tell me about the Horizon Forbidden West DLC."
            ],
            "responses": [
              "The Witcher 3 DLC includes Hearts of Stone and Blood and Wine expansions.",
              "Yes, the new Destiny 2 expansion adds missions, weapons, and maps.",
              "The Horizon Forbidden West DLC introduces a new region and story arc."
            ]
          },
    {
        "tag": "enchanted_sculptures",
        "patterns": [
            "Tell me about enchanted sculptures",
            "Statues with mystical powers",
            "Transformative art installations"
        ],
        "responses": [
            "Enchanted sculptures are artistic creations that possess magical properties or evoke a sense of wonder and awe.",
            "Sculptures are expressive forms of art that can evoke emotions, tell stories, and reflect cultural ideas."
        ]
    },
    {
        "tag": "wizarding_sports",
        "patterns": [
            "Playing wizarding sports",
            "Quidditch-like games in real life",
            "Magical athletes and their feats"
        ],
        "responses": [
            "Wizarding sports, like Quidditch from Harry Potter, showcase magical athleticism and exciting competitions.",
            "In the real world, sports and athletic competitions bring people together in a spirit of camaraderie and healthy competition."
        ]
    },
    {
        "tag": "enchanted_gems",
        "patterns": [
            "Unearthing enchanted gems",
            "Gemstones with mystical properties",
            "The power of gemstone magic"
        ],
        "responses": [
            "Enchanted gems are mythical gemstones that possess magical qualities, such as healing or granting wishes.",
            "Gemstones have long been treasured for their beauty, rarity, and symbolism."
        ]
    },
    {
        "tag": "timeless_wanderer",
        "patterns": [
            "The adventures of a timeless wanderer",
            "Roaming through eras and dimensions",
            "The wisdom of an eternal traveler"
        ],
        "responses": [
            "A timeless wanderer is a mythical figure, often depicted as an immortal or time-traveling being who observes the ebb and flow of history.",
            "Travelers in reality explore the world, experiencing diverse cultures and creating lasting memories."
        ]
    },
    {
        "tag": "enchanted_mirror_maze",
        "patterns": [
            "Getting lost in an enchanted mirror maze",
            "Reflections and illusions in the maze",
            "The challenge of finding the way out"
        ],
        "responses": [
            "An enchanted mirror maze is a bewitching labyrinth filled with reflections and optical illusions.",
            "Real-world mirror mazes are popular attractions that offer fun and disorienting experiences."
        ]
    },
    {
        "tag": "astral_artistry",
        "patterns": [
            "Exploring astral artistry",
            "Paintings that transcend dimensions",
            "Art that captures cosmic beauty"
        ],
        "responses": [
            "Astral artistry is an imaginative concept where art reflects celestial wonders and the mysteries of the universe.",
            "Artists use their creativity to portray their perceptions of the world and beyond."
        ]
    },
    {
        "tag": "enchanted_teapot",
        "patterns": [
            "Encountering an enchanted teapot",
            "Tea ceremonies in magical realms",
            "Teapot magic and rituals"
        ],
        "responses": [
            "An enchanted teapot is a fantastical vessel that brews magical tea with extraordinary properties.",
            "Tea ceremonies have cultural significance in various traditions and symbolize hospitality and connection."
        ]
    },
    {
        "tag": "timeless_ballroom",
        "patterns": [
            "Dancing in a timeless ballroom",
            "Elegant waltzes through the ages",
            "Time-traveling masquerade balls"
        ],
        "responses": [
            "A timeless ballroom is a mythical setting where dance transcends time, and participants waltz through different historical eras.",
            "Ballroom dancing is a graceful and expressive form of dance that has evolved over centuries."
        ]
    },
    {
        "tag": "enchanted_fog",
        "patterns": [
            "Encountering enchanted fog",
            "The mysteries within mystical mists",
            "Foggy journeys through magical lands"
        ],
        "responses": [
            "Enchanted fog is a magical phenomenon that cloaks landscapes in mystery and wonder.",
            "Fog is a natural meteorological condition caused by the condensation of water vapor in the air."
        ]
    },
    {
        "tag": "spellcasting_tournament",
        "patterns": [
            "Competing in a spellcasting tournament",
            "Magical duels and wizard battles",
            "The quest for the title of the grand spellcaster"
        ],
        "responses": [
            "Spellcasting tournaments are thrilling events where magic-users showcase their skills and compete for recognition and honor.",
            "Competitions and sports events celebrate talent, dedication, and teamwork."
        ]
    },
    {
        "tag": "enchanted_stardust",
        "patterns": [
            "Discovering enchanted stardust",
            "Cosmic particles with magical properties",
            "Wishes granted by stardust"
        ],
        "responses": [
            "Enchanted stardust is a mythical substance that is said to originate from the cosmos and hold magical properties.",
            "Stardust is a poetic term that refers to cosmic particles that form stars and planets."
        ]
    },
    {
        "tag": "fantastical_architecture",
        "patterns": [
            "Marveling at fantastical architecture",
            "Buildings that defy gravity and logic",
            "Designing dreamlike structures"
        ],
        "responses": [
            "Fantastical architecture is an artistic expression that pushes the boundaries of imagination, creating whimsical and surreal buildings.",
            "Architects and designers explore innovative ideas to shape the future of urban living."
        ]
    },
    {
        "tag": "enchanted_breeze",
        "patterns": [
            "Feeling the touch of an enchanted breeze",
            "The magic of gentle winds",
            "Whispers of mystical winds"
        ],
        "responses": [
            "An enchanted breeze is a mythical concept where gentle winds carry magic and blessings.",
            "The wind is a natural atmospheric phenomenon that influences weather patterns and is essential for the environment."
        ]
    },
    {
        "tag": "dragon_tamer",
        "patterns": [
            "Becoming a dragon tamer",
            "The art of befriending dragons",
            "Forming bonds with mythical beasts"
        ],
        "responses": [
            "Dragon tamers are legendary figures who form unique connections with dragons and earn their trust.",
            "Dragons symbolize power and wisdom in various cultures and mythologies."
        ]
    },
    {
        "tag": "enchanted_fruits",
        "patterns": [
            "Discovering enchanted fruits",
            "Fruits with mystical flavors and effects",
            "The magical properties of rare fruits"
        ],
        "responses": [
            "Enchanted fruits are mythical creations that possess extraordinary flavors or grant fantastical abilities.",
            "In reality, fruits are nutritious and delicious natural foods that offer a wide range of health benefits."
        ]
    },
    {
        "tag": "magical_mistakes",
        "patterns": [
            "Learning from magical mistakes",
            "Lessons in wizardry gone awry",
            "The humor and consequences of misfiring spells"
        ],
        "responses": [
            "Magical mistakes are comedic elements in fantasy stories where spells and enchantments don't go as planned.",
            "In real life, making mistakes is a part of learning and growing."
        ]
    },
    {
        "tag": "enchanted_rain",
        "patterns": [
            "Experiencing enchanted rain",
            "Rainfall that brings good fortune",
            "Dancing in the rain with magical properties"
        ],
        "responses": [
            "Enchanted rain is a fantastical concept where raindrops hold magical qualities, such as granting blessings or wishes.",
            "Rain is a natural weather phenomenon and an essential part of the water cycle."
        ]
    },
    {
        "tag": "timeless_tales",
        "patterns": [
            "Sharing timeless tales",
            "Storytelling that spans generations",
            "The magic of passing down stories"
        ],
        "responses": [
            "Timeless tales are enduring narratives that transcend time and continue to captivate audiences across generations.",
            "Storytelling is a powerful form of communication and cultural preservation."
        ]
    },
    {
        "tag": "enchanted_well",
        "patterns": [
            "Encountering an enchanted well",
            "Wishes granted by magical waters",
            "Seeking wisdom from the depths"
        ],
        "responses": [
            "An enchanted well is a mythical source of water that grants wishes or possesses healing properties.",
            "Wells have historical significance as vital sources of water for communities."
        ]
    },
    {
        "tag": "dimensional_doorway",
        "patterns": [
            "Opening a dimensional doorway",
            "Portals to parallel worlds",
            "Exploring alternate realities"
        ],
        "responses": [
            "A dimensional doorway is an imaginative concept that allows passage between different dimensions and realities.",
            "The idea of parallel universes and multiple dimensions is a popular theme in science fiction and theoretical physics."
        ]
    },
    {
        "tag": "enchanted_snow",
        "patterns": [
            "Witnessing enchanted snowfall",
            "The magic of snow in mythical realms",
            "The secrets of eternal snow"
        ],
        "responses": [
            "Enchanted snow is a mythical phenomenon where snowflakes possess magical properties or create enchanting winter landscapes.",
            "Snow is a meteorological event where frozen water crystals fall from the sky in colder climates."
        ]
    },
    {
        "tag": "spellbinding_cuisine",
        "patterns": [
            "Savoring spellbinding cuisine",
            "Food that delights the senses and soul",
            "Recipes from ancient spellbooks"
        ],
        "responses": [
            "Spellbinding cuisine is an imaginative concept where food is prepared with magical ingredients and flavors.",
            "Cooking and culinary arts offer diverse tastes and cultural experiences."
        ]
    },
    {
        "tag": "enchanted_lullabies",
        "patterns": [
            "Listening to enchanted lullabies",
            "Songs that soothe and enchant",
            "The magic of bedtime melodies"
        ],
        "responses": [
            "Enchanted lullabies are mythical songs that have a soothing and magical effect, lulling listeners into a peaceful slumber.",
            "Lullabies are cherished melodies that parents sing to their children to comfort and calm them."
        ]
    },
    {
        "tag": "time_travelers_journal",
        "patterns": [
            "Reading a time traveler's journal",
            "Chronicles of historical adventures",
            "Insights into the past and future"
        ],
        "responses": [
            "A time traveler's journal is a fictional account documenting journeys through different historical periods and possibly into the future.",
            "Historical records, memoirs, and diaries provide valuable insights into the past."
        ]
    },
    {
        "tag": "enchanted_stables",
        "patterns": [
            "Visiting enchanted stables",
            "Magical creatures and their stables",
            "Horses with mythical qualities"
        ],
        "responses": [
            "Enchanted stables are fantastical settings where mythical creatures, such as winged horses, are cared for and nurtured.",
            "Stables in reality house domesticated animals, providing shelter and care for their well-being."
        ]
    },
    {
        "tag": "wizarding_cuisine",
        "patterns": [
            "Exploring wizarding cuisine",
            "Magical ingredients and recipes",
            "Feasting in the grand wizarding halls"
        ],
        "responses": [
            "Wizarding cuisine is a fictional culinary world where food is prepared with magical flair and sometimes holds mystical properties.",
            "Culinary diversity and creativity are celebrated across different cultures."
        ]
    },
    {
        "tag": "enchanted_riddles",
        "patterns": [
            "Solving enchanted riddles",
            "Riddles that guard hidden treasures",
            "Wisdom and challenges in mythical riddles"
        ],
        "responses": [
            "Enchanted riddles are puzzles that challenge the mind and are often associated with quests and adventures in folklore and fantasy tales.",
            "Riddles have been used for entertainment and intellectual stimulation throughout history."
        ]
    },
    {
        "tag": "timeless_relics",
        "patterns": [
            "Discovering timeless relics",
            "Artifacts from lost civilizations",
            "The allure of ancient mysteries"
        ],
        "responses": [
            "Timeless relics are ancient artifacts and objects that hold historical and cultural significance, preserving the stories of our ancestors.",
            "Archaeologists and historians continue to unearth relics that shed light on human history and civilization."
        ]
    }
]
